[
  {
    "date": "2026-03-23T00:00:00.000Z",
    "title": "LA BIGOTTA",
    "venue": "FORLI, TEATRO DIEGO FABBRI",
    "performers": "ANTONIO REZZA, voce revitante\nFLAVIA MASTRELLA, videoart\nDANILO ROSSI, viola solista e direttore\nORCHESTRA MADERNA",
    "url": "https://www.forlimusica.it/concerti/la-bigotta"
  },
  {
    "date": "2026-04-12T00:00:00.000Z",
    "title": "RESPIRI DI QUIETE MOBILE",
    "venue": "L' AQUILA, AUDITORIUM DEL PARCO",
    "performers": "QUARTETTO DI SAXOFONI ACCADEMIA",
    "url": "https://barattelli.it/eventi/quartetto-di-saxofoni-accademia/"
  }
]